[
    {
        "file_path":"NajibIlham (3).pdf",
        "fulltext_extracted":"N A J I B I L H A M\n\u00c9TUDIANTE EN MASTER AI ET\nINFORMATIQUE DIGITALE \u2013\nD\u00c9VELOPPEUSE FULL-STACK\nForm\u00e9e en d\u00e9veloppement full-stack et en data science avec un\nfort int\u00e9r\u00eat pour l\u2019intelligence artificielle et le machine learning.\n\u00c0 la recherche d\u2019un PFA en IA, data science ou d\u00e9veloppement\nlogiciel. Motiv\u00e9e, polyvalente et passionn\u00e9e par les projets\ntechnologiques innovants et \u00e0 fort impact.\nCONTACT \u00c9DUCATION & DIPL\u00d4MES\n+212-608428694 Master en Intelligence Artificielle et Informatique Digitale\nFacult\u00e9 des Sciences et Techniques de Beni Mellal | 2024-2026\nLicence en Syst\u00e8mes Informatiques Distribu\u00e9s\nnajibilham841@gmail.com\nFacult\u00e9 des Sciences et Techniques de Marrakech | 2020-2023\nDEUST en Math\u00e9matiques, Informatique, Physique et Chimie\nnajib ilham\nFacult\u00e9 des Sciences et Techniques de Marrakech | 2023-2024\nBaccalaur\u00e9at en Sciences Physiques\nAgadir,Maroc\nColl\u00e8ge Abdellah Ben Yassine | 2019-2020\nEXP\u00c9RIENCE PROFESSIONNELLE\nCOMP\u00c9TENCES\nStage \u2013 D\u00e9veloppeur Web | Mars 2024 - Juin 2024\nD\u00e9veloppement de l'application web Zynerator\nLangages : Java, Python,\nD\u00e9veloppement d'une application web nomm\u00e9e Zynerator, une plateforme de g\u00e9n\u00e9ration de\nJavaScript, C, SQL,TypeScript\ncode pour les projets backend et frontend utilisant divers langages de programmation.\nFrameworks \/ Librairies : Spring Utilisation de Spring pour le d\u00e9veloppement backend et d'Angular pour le d\u00e9veloppement\nBoot, React, Scikitlearn, Pandas, frontend.\nNumPy,Angular,Pytorch\nBig Data : Hadoop, HDFS, FORMATIONS\nMapReduce, HBase, Docker, Data\nReplication,spark,kafka AI Fundamentals | 2024\nBases de donn\u00e9es : MySQL, Certificat en Fondamentaux de l'IA avec IBM SkillsBuild par Cisco\nGit and GitHub | 2024\nPostgreSQL, MongoDB,\nCertificat en Git et GitHub d\u00e9livr\u00e9 par 365 Data Science\nHBase,Neo4j\nMicrosoft Tech Day\nOutils : Git, GitHub,\nCertificat de participation au Microsoft Tech Day \u00e0 l'ENSA de Beni Mellal\nPostman,Trello\nRobotique et Cartes \u00c9lectroniques Programmables\nConcepts : API REST, POO,\nCertificat de participation \u00e0 une formation certifi\u00e9e ax\u00e9e sur\nAgile\/Scrum, Machine Learning, les fondamentaux de la robotique et des cartes \u00e9lectroniques programmables.\nDeep learning,Data Analysis\nPROJETS CL\u00c9S\nQUALIT\u00c9S\nSyst\u00e8me de Diagnostic M\u00e9dical :\nSyst\u00e8me de Diagnostic m\u00e9dical avec Python et Django.\nEsprit d\u2019\u00e9quipe et\nProjet Chatbot :\ncollaboration Chatbot NLP pour r\u00e9pondre aux questions.\nAutonomie et prise \u00c9tude des Performances Scolaires et Motivations :\nd\u2019initiative Analyse des performances scolaires via des m\u00e9thodes statistiques comme la r\u00e9gression\nCapacit\u00e9 \u00e0 r\u00e9soudre des lin\u00e9aire et l'ANOVA , SVM pour la classification.\nprobl\u00e8mes complexes D\u00e9tection de Maladies des Plantes (Machine Learning) :\nMod\u00e8le ML pour d\u00e9tecter les maladies des plantes \u00e0 partir d'images.\nPassion pour l\u2019innovation\nProjet Kafka :\nen IA\nCr\u00e9ation d\u2019une architecture de traitement de donn\u00e9es en temps r\u00e9el avec Apache Kafka et\nLANGUES l'API OpenSky Network..\nSmart Farm IoT :\nFran\u00e7ais, Anglais, Arabe Ferme intelligente avec IoT, contr\u00f4l\u00e9e \u00e0 distance via une application backend (Spring,\nPython) et frontend (React).",
        "gemini_json_extracted":"{\"certifications\":[\"Certificat en Fondamentaux de l'IA avec IBM SkillsBuild par Cisco\",\"Certificat en Git et GitHub d\u00e9livr\u00e9 par 365 Data Science\",\"Certificat de participation au Microsoft Tech Day \u00e0 l'ENSA de Beni Mellal\",\"Certificat de participation \u00e0 une formation certifi\u00e9e ax\u00e9e sur les fondamentaux de la robotique et des cartes \u00e9lectroniques programmables.\"],\"education\":[{\"degree\":\"Master en Intelligence Artificielle et Informatique Digitale\",\"graduation_year\":\"2026\",\"institution_name\":\"Facult\u00e9 des Sciences et Techniques de Beni Mellal\"},{\"degree\":\"DEUST en Math\u00e9matiques, Informatique, Physique et Chimie\",\"graduation_year\":\"2024\",\"institution_name\":\"Facult\u00e9 des Sciences et Techniques de Marrakech\"},{\"degree\":\"Licence en Syst\u00e8mes Informatiques Distribu\u00e9s\",\"graduation_year\":\"2023\",\"institution_name\":\"Facult\u00e9 des Sciences et Techniques de Marrakech\"},{\"degree\":\"Baccalaur\u00e9at en Sciences Physiques\",\"graduation_year\":\"2020\",\"institution_name\":\"Coll\u00e8ge Abdellah Ben Yassine\"}],\"email\":\"najibilham841@gmail.com\",\"experience\":[{\"company_name\":\"N\/A\",\"description\":\"D\u00e9veloppement d'une application web nomm\u00e9e Zynerator, une plateforme de g\u00e9n\u00e9ration de code pour les projets backend et frontend utilisant divers langages de programmation. Utilisation de Spring pour le d\u00e9veloppement backend et d'Angular pour le d\u00e9veloppement frontend.\",\"job_title\":\"D\u00e9veloppeur Web (Intern)\",\"years_worked\":\"Mars 2024 - Juin 2024\"}],\"languages\":[\"Fran\u00e7ais\",\"Anglais\",\"Arabe\"],\"name\":\"NAJIB ILHAM\",\"phone\":\"+212-608428694\",\"skills\":[\"Java\",\"Python\",\"JavaScript\",\"SQL\",\"TypeScript\",\"Spring Boot\",\"React\",\"Angular\",\"Machine Learning\",\"Deep Learning\",\"Data Analysis\",\"Hadoop\",\"Docker\",\"Kafka\",\"Git\"]}"
    }
]